timezone_adapter/__init__.py
timezone_adapter/main.py
timezone_adapter-0.1.0.dist-info/LICENSE
timezone_adapter-0.1.0.dist-info/METADATA
timezone_adapter-0.1.0.dist-info/WHEEL
timezone_adapter-0.1.0.dist-info/top_level.txt
timezone_adapter-0.1.0.dist-info/RECORD
