Metadata-Version: 2.1
Name: timezone-adapter
Version: 0.1.0
Summary: A class for converting and manipulating datetime objects based on given timezone offset or name.
Home-page: https://github.com/miguepoloc/timezone-adapter
Author: Miguel Angel Polo Castañeda
Author-email: Miguel Angel Polo Castañeda <miguepoloc@gmail.com>
License: MIT
Project-URL: Homepage, https://github.com/miguepoloc/timezone-adapter
Project-URL: Repository, https://github.com/miguepoloc/timezone-adapter.git
Keywords: timezone,datetime,converter
Classifier: Development Status :: 4 - Beta
Classifier: Programming Language :: Python :: 3
Classifier: Programming Language :: Python :: 3.12
Classifier: License :: OSI Approved :: MIT License
Requires-Python: >=3.6
License-File: LICENSE
Requires-Dist: pytz>=2022.1
Provides-Extra: dev
Requires-Dist: types-pytz>=2023.3.1.1; extra == "dev"
Requires-Dist: twine>=4.0.2; extra == "dev"
Requires-Dist: build>=1.0.3; extra == "dev"
Requires-Dist: types-setuptools>=69.0.0.0; extra == "dev"
Requires-Dist: mypy; extra == "dev"
Requires-Dist: black; extra == "dev"
Requires-Dist: isort; extra == "dev"
Requires-Dist: flake8; extra == "dev"
